{
  "wood_pickaxe": {
    "max": 1,
    "tags": {
      "fuel": "10"
    },
    "components": {
      "ItemDurableComponent": {
        "Name": "ItemDurableComponent",
        "Tag": "any|pickaxe",
        "ToolLevel": 0,
        "Efficiency": 1,
        "Max": 100,
        "Value": 100
      }
    }
  },
  "stone_pickaxe": {
    "max": 1,
    "components": {
      "ItemDurableComponent": {
        "Name": "ItemDurableComponent",
        "Tag": "any|pickaxe",
        "ToolLevel": 1,
        "Efficiency": 2,
        "Max": 250,
        "Value": 250
      }
    }
  },
  "iron_pickaxe": {
    "max": 1,
    "components": {
      "ItemDurableComponent": {
        "Name": "ItemDurableComponent",
        "Tag": "any|pickaxe",
        "ToolLevel": 2,
        "Efficiency": 3,
        "Max": 500,
        "Value": 500
      }
    }
  }
}